MANIFEST.in
README
setup.py
Pylatus/__init__.py
Pylatus/controller/__init__.py
Pylatus/controller/chunks.py
Pylatus/controller/config.py
Pylatus/controller/ctrl.py
Pylatus/controller/rmq.py
Pylatus/controller/utils.py
Pylatus/devices/__init__.py
Pylatus/devices/diffractometer.py
Pylatus/devices/monitor.py
Pylatus/devices/musst.py
Pylatus/devices/pilatus.py
Pylatus/devices/scanman.py
Pylatus/gui/__init__.py
Pylatus/gui/gutils.py
Pylatus/gui/qmotordialog.py
Pylatus/gui/wabout.py
Pylatus/gui/walign.py
Pylatus/gui/wmain.py
Pylatus/gui/woptions.py
Pylatus/gui/wrelmove.py
Pylatus/gui/wscan.py
Pylatus/gui/wstatus.py
Pylatus/gui/wuserstatus.py
Pylatus/gui/ui/__init__.py
Pylatus/gui/ui/resources_rc.py
Pylatus/gui/ui/ui_options.py
Pylatus/gui/ui/ui_scan_groupbox.py
Pylatus/gui/ui/ui_wabout.py
Pylatus/gui/ui/ui_walign.py
Pylatus/gui/ui/ui_wmain.py
Pylatus/gui/ui/ui_wrelmove.py
Pylatus/gui/ui/ui_wscan.py
Pylatus/gui/ui/ui_wstatus.py
Pylatus/gui/ui/ui_wuserstatus.py
Pylatus/scripo/__init__.py
Pylatus/scripo/diffractometer.py
Pylatus/scripo/musst.py
pylatus.egg-info/PKG-INFO
pylatus.egg-info/SOURCES.txt
pylatus.egg-info/dependency_links.txt
pylatus.egg-info/entry_points.txt
pylatus.egg-info/requires.txt
pylatus.egg-info/top_level.txt