Metadata-Version: 1.1
Name: pylatus
Version: 2018.1.22
Summary: Driver for diffractometers based on SPEC and Pilatus
Home-page: https://hg.3lp.cx/pylatus
Author: Vadim Dyadkin
Author-email: diadkin@esrf.fr
License: GPL
Platform: UNKNOWN
Classifier: License :: OSI Approved :: GNU General Public License v3 (GPLv3)
Classifier: Programming Language :: Python
Classifier: Programming Language :: Python :: 3.6
Classifier: Programming Language :: Python :: Implementation :: CPython
